pylogformats/__init__.py
pylogformats/baseline.py
pylogformats/json/__init__.py
pylogformats/json/advanced.py
pylogformats/json/bunyan.py
pylogformats/json/simple.py
pylogformats/py.typed
pylogformats/text/__init__.py
pylogformats/text/compact.py
pylogformats/text/simple.py
pylogformats-1.0.0.dist-info/LICENSE
pylogformats-1.0.0.dist-info/WHEEL
pylogformats-1.0.0.dist-info/METADATA
pylogformats-1.0.0.dist-info/RECORD
