Metadata-Version: 2.1
Name: pylogformats
Version: 1.0.0
Summary: PyLogFormats
Home-page: https://github.com/MattLimb/pylogformats
License: MIT
Author: Matt Limb
Author-email: matt.limb17@gmail.com
Requires-Python: >=3.7,<4.0
Classifier: Development Status :: 4 - Beta
Classifier: License :: OSI Approved :: MIT License
Classifier: Programming Language :: Python :: 3
Classifier: Programming Language :: Python :: 3.10
Classifier: Programming Language :: Python :: 3.7
Classifier: Programming Language :: Python :: 3.8
Classifier: Programming Language :: Python :: 3.9
Project-URL: Changelog, https://github.com/MattLimb/pylogformats/releases
Project-URL: Documentation, https://pylogformats.readthedocs.io
Project-URL: Repository, https://github.com/MattLimb/pylogformats
